{"index": 65, "name": "Ethiopia", "code": "ETH", "number": 190, "number_of_attacks": 190, "number_of_fatalities": 1765, "most_attacks": "Bombing/Explosion", "top_perpetrators": [{"x_axis": "Unknown", "y_axis": 86}, {"x_axis": "Eritrean Liberation Front", "y_axis": 20}, {"x_axis": "Murle Tribe", "y_axis": 15}, {"x_axis": "Tigray Peoples Liberation Front (TPLF)", "y_axis": 11}, {"x_axis": "Patriotic Ginbot 7 Movement for Unity and Democracy (PGMUD)", "y_axis": 11}, {"x_axis": "Oromo Liberation Front", "y_axis": 7}, {"x_axis": "Al-Shabaab", "y_axis": 6}, {"x_axis": "Ethiopian People's Revolutionary Party", "y_axis": 5}, {"x_axis": "Ogaden National Liberation Front (ONLF)", "y_axis": 5}, {"x_axis": "Coalition for Unity and Democracy (CUD)", "y_axis": 4}, {"x_axis": "Afar Revolutionary Democratic Unity Front", "y_axis": 3}, {"x_axis": "Eritrean Peoples Liberation Front", "y_axis": 3}, {"x_axis": "Al-Ittihaad al-Islami (AIAI)", "y_axis": 2}, {"x_axis": "Tepi Youth", "y_axis": 2}, {"x_axis": "Somali Islamic Front", "y_axis": 1}, {"x_axis": "Somali Guerrillas", "y_axis": 1}, {"x_axis": "Former members Central Investigation Office", "y_axis": 1}, {"x_axis": "Issa and Gurgura Liberation Front", "y_axis": 1}, {"x_axis": "Al-Gama'at al-Islamiyya (IG)", "y_axis": 1}, {"x_axis": "Benishangul Gumuz People's Liberation Movement", "y_axis": 1}, {"x_axis": "Bandits", "y_axis": 1}, {"x_axis": "Amhara tribal group", "y_axis": 1}, {"x_axis": "All Ethiopian Unity Party (AEUP)", "y_axis": 1}, {"x_axis": "Western Somalia Liberation Front", "y_axis": 1}], "perpetrators_chart": [{"x_axis": "Unknown", "y_axis": 86}, {"x_axis": "Eritrean Liberation Front", "y_axis": 20}, {"x_axis": "Murle Tribe", "y_axis": 15}, {"x_axis": "Tigray Peoples Liberation Front (TPLF)", "y_axis": 11}, {"x_axis": "Patriotic Ginbot 7 Movement for Unity and Democracy (PGMUD)", "y_axis": 11}, {"x_axis": "Oromo Liberation Front", "y_axis": 7}, {"x_axis": "Al-Shabaab", "y_axis": 6}, {"x_axis": "Ethiopian People's Revolutionary Party", "y_axis": 5}, {"x_axis": "Ogaden National Liberation Front (ONLF)", "y_axis": 5}, {"x_axis": "Coalition for Unity and Democracy (CUD)", "y_axis": 4}, {"x_axis": "Afar Revolutionary Democratic Unity Front", "y_axis": 3}, {"x_axis": "Eritrean Peoples Liberation Front", "y_axis": 3}, {"x_axis": "Tepi Youth", "y_axis": 2}, {"x_axis": "Al-Ittihaad al-Islami (AIAI)", "y_axis": 2}, {"x_axis": "Somali Islamic Front", "y_axis": 1}, {"x_axis": "Somali Guerrillas", "y_axis": 1}, {"x_axis": "Former members Central Investigation Office", "y_axis": 1}, {"x_axis": "Issa and Gurgura Liberation Front", "y_axis": 1}, {"x_axis": "Al-Gama'at al-Islamiyya (IG)", "y_axis": 1}, {"x_axis": "Benishangul Gumuz People's Liberation Movement", "y_axis": 1}, {"x_axis": "Bandits", "y_axis": 1}, {"x_axis": "Amhara tribal group", "y_axis": 1}, {"x_axis": "All Ethiopian Unity Party (AEUP)", "y_axis": 1}, {"x_axis": "Western Somalia Liberation Front", "y_axis": 1}], "attack_chart": [{"x_axis": "Bombing/Explosion", "y_axis": 78}, {"x_axis": "Hostage Taking (Kidnapping)", "y_axis": 42}, {"x_axis": "Armed Assault", "y_axis": 33}, {"x_axis": "Assassination", "y_axis": 11}, {"x_axis": "Unknown", "y_axis": 11}, {"x_axis": "Hijacking", "y_axis": 8}, {"x_axis": "Facility/Infrastructure Attack", "y_axis": 5}, {"x_axis": "Hostage Taking (Barricade Incident)", "y_axis": 2}]}
