{"index": 603, "name": "United Kingdom", "code": "GBR", "number": 5235, "number_of_attacks": 5235, "number_of_fatalities": 3410, "most_attacks": "Bombing/Explosion", "top_perpetrators": [{"x_axis": "Irish Republican Army (IRA)", "y_axis": 2575}, {"x_axis": "Unknown", "y_axis": 958}, {"x_axis": "Protestant extremists", "y_axis": 328}, {"x_axis": "Ulster Volunteer Force (UVF)", "y_axis": 261}, {"x_axis": "Ulster Freedom Fighters (UFF)", "y_axis": 218}, {"x_axis": "Irish National Liberation Army (INLA)", "y_axis": 113}, {"x_axis": "Irish Republican Extremists", "y_axis": 94}, {"x_axis": "Dissident Republicans", "y_axis": 89}, {"x_axis": "Oglaigh na hEireann", "y_axis": 48}, {"x_axis": "The New Irish Republican Army", "y_axis": 42}, {"x_axis": "Official Irish Republican Army (OIRA)", "y_axis": 38}, {"x_axis": "Real Irish Republican Army (RIRA)", "y_axis": 38}, {"x_axis": "Loyalists", "y_axis": 32}, {"x_axis": "Meibion Glyndwr", "y_axis": 31}, {"x_axis": "Continuity Irish Republican Army (CIRA)", "y_axis": 30}, {"x_axis": "Animal Liberation Front (ALF)", "y_axis": 24}, {"x_axis": "Red Hand Defenders (RHD)", "y_axis": 23}, {"x_axis": "Loyalist Volunteer Forces (LVF)", "y_axis": 22}, {"x_axis": "Irish People's Liberation Organization (IPLO)", "y_axis": 20}, {"x_axis": "Anti-Muslim extremists", "y_axis": 14}, {"x_axis": "Animal Rights extremists", "y_axis": 14}, {"x_axis": "Orange Volunteers (OV)", "y_axis": 11}, {"x_axis": "Black September", "y_axis": 10}, {"x_axis": "Informal Anarchist Federation", "y_axis": 9}, {"x_axis": "Al-Qaida", "y_axis": 8}, {"x_axis": "Red Hand Commandos", "y_axis": 8}, {"x_axis": "Qaddafi loyalists", "y_axis": 8}, {"x_axis": "Anarchists", "y_axis": 7}, {"x_axis": "Scottish National Liberation Army", "y_axis": 7}, {"x_axis": "Guerrillas", "y_axis": 6}, {"x_axis": "Muslim extremists", "y_axis": 6}, {"x_axis": "Republican Action Force", "y_axis": 6}, {"x_axis": "Protestant Action Group", "y_axis": 5}, {"x_axis": "Unemployed Persons", "y_axis": 5}, {"x_axis": "Armenian Secret Army for the Liberation of Armenia", "y_axis": 5}, {"x_axis": "White extremists", "y_axis": 5}, {"x_axis": "Kurdish Dissidents", "y_axis": 4}, {"x_axis": "Jihadi-inspired extremists", "y_axis": 4}, {"x_axis": "Direct Action Against Drugs (DADD)", "y_axis": 4}, {"x_axis": "Real Ulster Freedom Fighters (UFF) - Northern Ireland", "y_axis": 4}, {"x_axis": "Column 88", "y_axis": 4}, {"x_axis": "Neo-Nazi extremists", "y_axis": 4}, {"x_axis": "Anti-Semitic extremists", "y_axis": 4}, {"x_axis": "Welsh Extremists", "y_axis": 4}, {"x_axis": "2 April Group", "y_axis": 3}, {"x_axis": "Catholic Reaction Force", "y_axis": 3}, {"x_axis": "Black Liberation Front", "y_axis": 3}, {"x_axis": "Army for Freeing Scotland", "y_axis": 3}, {"x_axis": "1st of May Group", "y_axis": 2}, {"x_axis": "Guardians of the Islamic Revolution", "y_axis": 2}, {"x_axis": "South East Antrim Brigade", "y_axis": 2}, {"x_axis": "Islamic State of Iraq and the Levant (ISIL)", "y_axis": 2}, {"x_axis": "Popular Front for the Liberation of Palestine (PFLP)", "y_axis": 2}, {"x_axis": "Scottish Socialist Republican League", "y_axis": 2}, {"x_axis": "Angry Brigade", "y_axis": 2}, {"x_axis": "Animal Rights Militia", "y_axis": 2}, {"x_axis": "Dark Harvest", "y_axis": 2}, {"x_axis": "Combat 18", "y_axis": 2}, {"x_axis": "Jewish Defense League (JDL)", "y_axis": 2}, {"x_axis": "South Londonderry Volunteers (SLV)", "y_axis": 2}, {"x_axis": "Terrorists", "y_axis": 1}, {"x_axis": "White Wolves (UK)", "y_axis": 1}, {"x_axis": "Welsh nationalists", "y_axis": 1}, {"x_axis": "Provisional RSPCA", "y_axis": 1}, {"x_axis": "The Irish Volunteers", "y_axis": 1}, {"x_axis": "Republican Action Against Drugs (RAAD)", "y_axis": 1}, {"x_axis": "Supporters of Johnny Adair", "y_axis": 1}, {"x_axis": "Random Anarchists", "y_axis": 1}, {"x_axis": "Red Brigades", "y_axis": 1}, {"x_axis": "Soldiers of the Algerian Opposition", "y_axis": 1}, {"x_axis": "Red Commandos", "y_axis": 1}, {"x_axis": "Red Flag", "y_axis": 1}, {"x_axis": "Scottish Nationalists", "y_axis": 1}, {"x_axis": "Prisoner's Action Force", "y_axis": 1}, {"x_axis": "Left-wing extremists", "y_axis": 1}, {"x_axis": "People's Liberation Army (Northern Ireland)", "y_axis": 1}, {"x_axis": "Arab Liberation Front (ALF)", "y_axis": 1}, {"x_axis": "Borderless Solidarity Cell (BSC)", "y_axis": 1}, {"x_axis": "Black December", "y_axis": 1}, {"x_axis": "Babbar Khalsa International (BKI)", "y_axis": 1}, {"x_axis": "Armenians", "y_axis": 1}, {"x_axis": "Arm na Poblachta' (Army of the Republic)", "y_axis": 1}, {"x_axis": "Arab Revolutionary Army", "y_axis": 1}, {"x_axis": "Arab Liberation Army", "y_axis": 1}, {"x_axis": "Paramilitary members", "y_axis": 1}, {"x_axis": "Anti-Iran Government Exiles", "y_axis": 1}, {"x_axis": "Animal Defense League", "y_axis": 1}, {"x_axis": "Angry Foxes Cell", "y_axis": 1}, {"x_axis": "Al-Qaida in the Arabian Peninsula (AQAP)", "y_axis": 1}, {"x_axis": "Al-Qaida in Iraq", "y_axis": 1}, {"x_axis": "Abu Nidal Organization (ANO)", "y_axis": 1}, {"x_axis": "Dissident", "y_axis": 1}, {"x_axis": "English Defense League (EDL)", "y_axis": 1}, {"x_axis": "Hutu extremists", "y_axis": 1}, {"x_axis": "Jammu and Kashmir Liberation Front", "y_axis": 1}, {"x_axis": "Justice Commandos for the Armenian Genocide", "y_axis": 1}, {"x_axis": "King Street", "y_axis": 1}, {"x_axis": "Kurdish Protestors", "y_axis": 1}, {"x_axis": "Kurdistan Workers' Party (PKK)", "y_axis": 1}, {"x_axis": "Libyan Students", "y_axis": 1}, {"x_axis": "Loyalist Action Force", "y_axis": 1}, {"x_axis": "May 15 Organization for the Liberation of Palestine", "y_axis": 1}, {"x_axis": "Militant Welsh", "y_axis": 1}, {"x_axis": "Muslim Fundamentalists", "y_axis": 1}, {"x_axis": "National Front for the Liberation of Cuba (FLNC)", "y_axis": 1}, {"x_axis": "Organization of Mujahadin of Islam", "y_axis": 1}, {"x_axis": "Palestinians", "y_axis": 1}, {"x_axis": "Paramilitaries", "y_axis": 1}, {"x_axis": "Youths", "y_axis": 1}], "perpetrators_chart": [{"x_axis": "Irish Republican Army (IRA)", "y_axis": 2575}, {"x_axis": "Unknown", "y_axis": 958}, {"x_axis": "Protestant extremists", "y_axis": 328}, {"x_axis": "Ulster Volunteer Force (UVF)", "y_axis": 261}, {"x_axis": "Ulster Freedom Fighters (UFF)", "y_axis": 218}, {"x_axis": "Irish National Liberation Army (INLA)", "y_axis": 113}, {"x_axis": "Irish Republican Extremists", "y_axis": 94}, {"x_axis": "Dissident Republicans", "y_axis": 89}, {"x_axis": "Oglaigh na hEireann", "y_axis": 48}, {"x_axis": "The New Irish Republican Army", "y_axis": 42}, {"x_axis": "Official Irish Republican Army (OIRA)", "y_axis": 38}, {"x_axis": "Real Irish Republican Army (RIRA)", "y_axis": 38}, {"x_axis": "Loyalists", "y_axis": 32}, {"x_axis": "Meibion Glyndwr", "y_axis": 31}, {"x_axis": "Continuity Irish Republican Army (CIRA)", "y_axis": 30}, {"x_axis": "Animal Liberation Front (ALF)", "y_axis": 24}, {"x_axis": "Red Hand Defenders (RHD)", "y_axis": 23}, {"x_axis": "Loyalist Volunteer Forces (LVF)", "y_axis": 22}, {"x_axis": "Irish People's Liberation Organization (IPLO)", "y_axis": 20}, {"x_axis": "Anti-Muslim extremists", "y_axis": 14}, {"x_axis": "Animal Rights extremists", "y_axis": 14}, {"x_axis": "Orange Volunteers (OV)", "y_axis": 11}, {"x_axis": "Black September", "y_axis": 10}, {"x_axis": "Informal Anarchist Federation", "y_axis": 9}, {"x_axis": "Red Hand Commandos", "y_axis": 8}, {"x_axis": "Qaddafi loyalists", "y_axis": 8}, {"x_axis": "Al-Qaida", "y_axis": 8}, {"x_axis": "Scottish National Liberation Army", "y_axis": 7}, {"x_axis": "Anarchists", "y_axis": 7}, {"x_axis": "Guerrillas", "y_axis": 6}, {"x_axis": "Muslim extremists", "y_axis": 6}, {"x_axis": "Republican Action Force", "y_axis": 6}, {"x_axis": "Protestant Action Group", "y_axis": 5}, {"x_axis": "Unemployed Persons", "y_axis": 5}, {"x_axis": "Armenian Secret Army for the Liberation of Armenia", "y_axis": 5}, {"x_axis": "White extremists", "y_axis": 5}, {"x_axis": "Column 88", "y_axis": 4}, {"x_axis": "Welsh Extremists", "y_axis": 4}, {"x_axis": "Anti-Semitic extremists", "y_axis": 4}, {"x_axis": "Neo-Nazi extremists", "y_axis": 4}, {"x_axis": "Real Ulster Freedom Fighters (UFF) - Northern Ireland", "y_axis": 4}, {"x_axis": "Direct Action Against Drugs (DADD)", "y_axis": 4}, {"x_axis": "Jihadi-inspired extremists", "y_axis": 4}, {"x_axis": "Kurdish Dissidents", "y_axis": 4}, {"x_axis": "2 April Group", "y_axis": 3}, {"x_axis": "Catholic Reaction Force", "y_axis": 3}, {"x_axis": "Black Liberation Front", "y_axis": 3}, {"x_axis": "Army for Freeing Scotland", "y_axis": 3}, {"x_axis": "South Londonderry Volunteers (SLV)", "y_axis": 2}, {"x_axis": "Jewish Defense League (JDL)", "y_axis": 2}, {"x_axis": "Combat 18", "y_axis": 2}, {"x_axis": "Dark Harvest", "y_axis": 2}, {"x_axis": "Animal Rights Militia", "y_axis": 2}, {"x_axis": "Angry Brigade", "y_axis": 2}, {"x_axis": "Scottish Socialist Republican League", "y_axis": 2}, {"x_axis": "Islamic State of Iraq and the Levant (ISIL)", "y_axis": 2}, {"x_axis": "South East Antrim Brigade", "y_axis": 2}, {"x_axis": "Guardians of the Islamic Revolution", "y_axis": 2}, {"x_axis": "1st of May Group", "y_axis": 2}, {"x_axis": "Popular Front for the Liberation of Palestine (PFLP)", "y_axis": 2}, {"x_axis": "Abu Nidal Organization (ANO)", "y_axis": 1}, {"x_axis": "Jammu and Kashmir Liberation Front", "y_axis": 1}, {"x_axis": "Hutu extremists", "y_axis": 1}, {"x_axis": "English Defense League (EDL)", "y_axis": 1}, {"x_axis": "Dissident", "y_axis": 1}, {"x_axis": "Angry Foxes Cell", "y_axis": 1}, {"x_axis": "Al-Qaida in Iraq", "y_axis": 1}, {"x_axis": "Al-Qaida in the Arabian Peninsula (AQAP)", "y_axis": 1}, {"x_axis": "King Street", "y_axis": 1}, {"x_axis": "Animal Defense League", "y_axis": 1}, {"x_axis": "Justice Commandos for the Armenian Genocide", "y_axis": 1}, {"x_axis": "Kurdistan Workers' Party (PKK)", "y_axis": 1}, {"x_axis": "Kurdish Protestors", "y_axis": 1}, {"x_axis": "Paramilitary members", "y_axis": 1}, {"x_axis": "Libyan Students", "y_axis": 1}, {"x_axis": "Loyalist Action Force", "y_axis": 1}, {"x_axis": "May 15 Organization for the Liberation of Palestine", "y_axis": 1}, {"x_axis": "Militant Welsh", "y_axis": 1}, {"x_axis": "Muslim Fundamentalists", "y_axis": 1}, {"x_axis": "National Front for the Liberation of Cuba (FLNC)", "y_axis": 1}, {"x_axis": "Organization of Mujahadin of Islam", "y_axis": 1}, {"x_axis": "Palestinians", "y_axis": 1}, {"x_axis": "Paramilitaries", "y_axis": 1}, {"x_axis": "Anti-Iran Government Exiles", "y_axis": 1}, {"x_axis": "Arm na Poblachta' (Army of the Republic)", "y_axis": 1}, {"x_axis": "Arab Liberation Army", "y_axis": 1}, {"x_axis": "Arab Revolutionary Army", "y_axis": 1}, {"x_axis": "Terrorists", "y_axis": 1}, {"x_axis": "White Wolves (UK)", "y_axis": 1}, {"x_axis": "Welsh nationalists", "y_axis": 1}, {"x_axis": "Provisional RSPCA", "y_axis": 1}, {"x_axis": "The Irish Volunteers", "y_axis": 1}, {"x_axis": "Republican Action Against Drugs (RAAD)", "y_axis": 1}, {"x_axis": "Supporters of Johnny Adair", "y_axis": 1}, {"x_axis": "Random Anarchists", "y_axis": 1}, {"x_axis": "Red Brigades", "y_axis": 1}, {"x_axis": "Soldiers of the Algerian Opposition", "y_axis": 1}, {"x_axis": "Red Commandos", "y_axis": 1}, {"x_axis": "Red Flag", "y_axis": 1}, {"x_axis": "Scottish Nationalists", "y_axis": 1}, {"x_axis": "Prisoner's Action Force", "y_axis": 1}, {"x_axis": "Left-wing extremists", "y_axis": 1}, {"x_axis": "People's Liberation Army (Northern Ireland)", "y_axis": 1}, {"x_axis": "Arab Liberation Front (ALF)", "y_axis": 1}, {"x_axis": "Borderless Solidarity Cell (BSC)", "y_axis": 1}, {"x_axis": "Black December", "y_axis": 1}, {"x_axis": "Babbar Khalsa International (BKI)", "y_axis": 1}, {"x_axis": "Armenians", "y_axis": 1}, {"x_axis": "Youths", "y_axis": 1}], "attack_chart": [{"x_axis": "Bombing/Explosion", "y_axis": 2092}, {"x_axis": "Assassination", "y_axis": 1651}, {"x_axis": "Armed Assault", "y_axis": 670}, {"x_axis": "Facility/Infrastructure Attack", "y_axis": 652}, {"x_axis": "Hostage Taking (Kidnapping)", "y_axis": 53}, {"x_axis": "Unarmed Assault", "y_axis": 46}, {"x_axis": "Unknown", "y_axis": 38}, {"x_axis": "Hijacking", "y_axis": 19}, {"x_axis": "Hostage Taking (Barricade Incident)", "y_axis": 14}]}
